{
  "actorSpecification": 1,
  "fields": {},
  "views": {
    "overview": {
      "title": "Overview",
      "transformation": {
        "fields": [
          "id",
          "shortcode",
          "title",
          "company",
          "company_logo",
          "location",
          "country",
          "workplace_type",
          "department",
          "employment_type",
          "job_types",
          "salary",
          "date_posted",
          "valid_through",
          "description_text",
          "url"
        ]
      },
      "display": {
        "component": "table",
        "properties": {
          "title": {
            "label": "Job Title",
            "format": "text"
          },
          "company": {
            "label": "Company",
            "format": "text"
          },
          "location": {
            "label": "Location",
            "format": "text"
          },
          "workplace_type": {
            "label": "Remote/On-site",
            "format": "text"
          },
          "department": {
            "label": "Department",
            "format": "text"
          },
          "employment_type": {
            "label": "Employment Type",
            "format": "text"
          },
          "salary": {
            "label": "Salary",
            "format": "text"
          },
          "date_posted": {
            "label": "Posted",
            "format": "text"
          },
          "url": {
            "label": "URL",
            "format": "link"
          }
        }
      }
    }
  }
}